mcp_aiven/main.py
mcp_aiven/mcp_env.py
mcp_aiven/mcp_server.py
iflow_mcp_mcp_aiven-0.1.4.dist-info/METADATA
iflow_mcp_mcp_aiven-0.1.4.dist-info/WHEEL
iflow_mcp_mcp_aiven-0.1.4.dist-info/entry_points.txt
iflow_mcp_mcp_aiven-0.1.4.dist-info/licenses/LICENSE
iflow_mcp_mcp_aiven-0.1.4.dist-info/RECORD
